reqs/__init__.py
reqs/cli.py
reqs/config.py
reqs/utils.py
reqs/version.py
reqs/libs/__init__.py
reqs/libs/testing.py
reqs/tests/__init__.py
reqs/tests/test_cli.py
reqs/tests/test_utils.py
reqs/tests/pkg-upgrade/pyproject.toml
reqs/tests/pkg-upgrade/requirements/alpha.in
reqs/tests/pkg-upgrade/requirements/bravo.in
reqs/tests/pkg-upgrade/requirements/charlie.in
reqs/tests/pkg1/pyproject.toml
reqs/tests/pkg1/foo/.gitkeep
reqs/tests/pkg1/requirements/alpha.in
reqs/tests/pkg1/requirements/bravo.in
reqs/tests/pkg1/requirements/charlie.in
reqs/tests/pkg2/pyproject.toml
reqs/tests/pkg3/pyproject.toml
reqs/tests/pkg3/requirements/base.in
reqs/tests/pkg4/pyproject.toml
reqs/tests/pkg4/requirements/base.in
reqs/tests/pkg4/requirements/foo.in
reqs/tests/pkg5/pyproject.toml
reqs/tests/pkg5/requirements/alpha.in
reqs/tests/pkg5/requirements/bravo.in
reqs_cli-0.20240711.2.dist-info/METADATA
reqs_cli-0.20240711.2.dist-info/WHEEL
reqs_cli-0.20240711.2.dist-info/entry_points.txt
reqs_cli-0.20240711.2.dist-info/RECORD
